scrapecsv/__init__.py
scrapecsv/scrapecsv.py
scrapecsv-1.1.0.dist-info/METADATA
scrapecsv-1.1.0.dist-info/WHEEL
scrapecsv-1.1.0.dist-info/licenses/LICENSE.txt
scrapecsv-1.1.0.dist-info/RECORD
